hawks/__init__.py
hawks/analysis.py
hawks/cluster.py
hawks/clustering.py
hawks/constraints.py
hawks/dataset.py
hawks/defaults.json
hawks/ga.py
hawks/generator.py
hawks/genotype.py
hawks/hawks_gen.py
hawks/io.py
hawks/mutation_testbed.py
hawks/objectives.py
hawks/plotting.py
hawks/prepare.py
hawks/problem_features.py
hawks/utils.py
hawks-0.2.0.dist-info/LICENSE.txt
hawks-0.2.0.dist-info/METADATA
hawks-0.2.0.dist-info/WHEEL
hawks-0.2.0.dist-info/top_level.txt
hawks-0.2.0.dist-info/RECORD
