Metadata-Version: 2.1
Name: hawks
Version: 0.2.0
Summary: A package for generating synthetic clusters, with parameters to customize different aspects of the complexity of the cluster structure
Home-page: https://github.com/sea-shunned/hawks
Author: Cameron Shand
Author-email: cameron.shand@manchester.ac.uk
License: MIT License
Project-URL: Documentation, https://hawks.readthedocs.io/
Platform: UNKNOWN
Classifier: License :: OSI Approved :: MIT License
Classifier: Operating System :: OS Independent
Classifier: Intended Audience :: Science/Research
Classifier: Programming Language :: Python :: 3.6
Classifier: Topic :: Scientific/Engineering :: Artificial Intelligence
Requires-Python: >=3.6
Requires-Dist: deap (==1.2.2)
Requires-Dist: matplotlib (>=3.0)
Requires-Dist: numpy (>=1.15)
Requires-Dist: orange3 (>=3.23)
Requires-Dist: pandas (>=0.23)
Requires-Dist: scikit-learn (>=0.20)
Requires-Dist: scipy (>=1.1)
Requires-Dist: seaborn (>=0.9.0)
Requires-Dist: tqdm (>=4.15)
